python_chess_gui/__init__.py
python_chess_gui/constants.py
python_chess_gui/layout_manager.py
python_chess_gui/main.py
python_chess_gui/core/__init__.py
python_chess_gui/core/coordinate_converter.py
python_chess_gui/core/game_state_manager.py
python_chess_gui/engine/__init__.py
python_chess_gui/engine/config_manager.py
python_chess_gui/engine/stockfish_engine_controller.py
python_chess_gui/input/__init__.py
python_chess_gui/input/user_input_handler.py
python_chess_gui/rendering/__init__.py
python_chess_gui/rendering/chess_board_renderer.py
python_chess_gui/rendering/evaluation_bar_renderer.py
python_chess_gui/rendering/game_settings_menu.py
python_chess_gui/rendering/game_status_display.py
python_chess_gui-0.1.4.dist-info/METADATA
python_chess_gui-0.1.4.dist-info/WHEEL
python_chess_gui-0.1.4.dist-info/entry_points.txt
python_chess_gui-0.1.4.dist-info/licenses/LICENSE
python_chess_gui-0.1.4.dist-info/RECORD
