Metadata-Version: 2.4
Name: python-chess-gui
Version: 0.1.4
Summary: A Python chess GUI application using pygame and python-chess with Stockfish support
Project-URL: Homepage, https://github.com/Bobain/python-chess-gui
Project-URL: Repository, https://github.com/Bobain/python-chess-gui
Project-URL: Issues, https://github.com/Bobain/python-chess-gui/issues
Author-email: Bobain <bobain@users.noreply.github.com>
License: MIT
License-File: LICENSE
Keywords: chess,game,gui,pygame,stockfish
Classifier: Development Status :: 4 - Beta
Classifier: Intended Audience :: End Users/Desktop
Classifier: License :: OSI Approved :: MIT License
Classifier: Operating System :: MacOS
Classifier: Operating System :: POSIX :: Linux
Classifier: Programming Language :: Python :: 3
Classifier: Programming Language :: Python :: 3.12
Classifier: Topic :: Games/Entertainment :: Board Games
Requires-Python: >=3.12
Requires-Dist: chess>=1.11.2
Requires-Dist: pygame>=2.6.1
